{"version":1,"resource":"vscode-remote://ssh-remote%2B192.168.19.130/home/sss/SSS-HA/resources/views/cars/create.blade.php","entries":[{"id":"J1Ca.php","timestamp":1705058134136},{"id":"YcZp.php","timestamp":1705058466918},{"id":"MllS.php","timestamp":1705058502857},{"id":"SbGN.php","timestamp":1705058539265},{"id":"6lWY.php","timestamp":1705058554952},{"id":"6cAn.php","timestamp":1705058576800},{"id":"BaYK.php","timestamp":1705058604956},{"id":"6w0W.php","timestamp":1705059531357},{"id":"hVnk.php","timestamp":1705060041556},{"id":"0lzL.php","timestamp":1705060054183},{"id":"kzjs.php","timestamp":1705060068059},{"id":"H3Jx.php","timestamp":1705060088430},{"id":"q4zC.php","timestamp":1705060151679},{"id":"y4Zb.php","timestamp":1705060629842},{"id":"IuY9.php","timestamp":1705060646225},{"id":"ZLt5.php","timestamp":1705060700212},{"id":"3stP.php","timestamp":1705060726251},{"id":"YANw.php","source":"undoRedo.source","timestamp":1705060736991},{"id":"3LaT.php","timestamp":1705060923103},{"id":"QYWs.php","source":"undoRedo.source","timestamp":1705060930895},{"id":"MKZt.php","timestamp":1705060931907},{"id":"HnK3.php","timestamp":1705062941692},{"id":"3jFS.php","source":"localHistoryRestore.source","timestamp":1705062974089},{"id":"7fzR.php","timestamp":1705062976052},{"id":"EzLZ.php","timestamp":1705064706621}]}